wmt2ics/__init__.py
wmt2ics/configemail.py
wmt2ics/sendemail.py
wmt2ics/shift_cats.data
wmt2ics/wmtconfig.json
Wmt2Ics-0.0.23.dist-info/LICENSE.txt
Wmt2Ics-0.0.23.dist-info/METADATA
Wmt2Ics-0.0.23.dist-info/WHEEL
Wmt2Ics-0.0.23.dist-info/top_level.txt
Wmt2Ics-0.0.23.dist-info/RECORD
