Metadata-Version: 2.1
Name: Wmt2Ics
Version: 0.0.23
Summary: Converts wmt schedule Views:My Schedule to .ics file
Home-page: https://github.com/mhr320/Wmt2Ics
Author: M. Holbert Roberts
Author-email: mhr320@gmail.com
License: UNKNOWN
Platform: UNKNOWN
Classifier: Development Status :: 3 - Alpha
Classifier: Programming Language :: Python :: 3
Classifier: License :: OSI Approved :: MIT License
Classifier: Operating System :: OS Independent
Classifier: Intended Audience :: Developers
Requires-Python: >=3.8, <4
License-File: LICENSE.txt
Requires-Dist: icalendar
Requires-Dist: pyperclip
